README.rst
setup.py
sqlalchemy_sql_shell.py
sqlalchemy_sql_shell.egg-info/PKG-INFO
sqlalchemy_sql_shell.egg-info/SOURCES.txt
sqlalchemy_sql_shell.egg-info/dependency_links.txt
sqlalchemy_sql_shell.egg-info/entry_points.txt
sqlalchemy_sql_shell.egg-info/not-zip-safe
sqlalchemy_sql_shell.egg-info/pbr.json
sqlalchemy_sql_shell.egg-info/requires.txt
sqlalchemy_sql_shell.egg-info/top_level.txt