Metadata-Version: 1.1
Name: sqlalchemy-sql-shell
Version: 0.0.0
Summary: A shell for doing simple SQL queries to any database supported by SQLAlchemy
Home-page: https://github.com/msabramo/sqlalchemy_sql_shell
Author: Marc Abramowitz
Author-email: marc@marc-abramowitz.com
License: MIT
Keywords: database,SQL,SQLAlchemy
Platform: UNKNOWN
Classifier: Programming Language :: Python :: 2
Classifier: Programming Language :: Python :: 2.5
Classifier: Programming Language :: Python :: 2.6
Classifier: Programming Language :: Python :: 2.7
Classifier: Programming Language :: Python :: 3
Classifier: Programming Language :: Python :: 3.0
Classifier: Programming Language :: Python :: 3.1
Classifier: Programming Language :: Python :: 3.2
Classifier: Programming Language :: Python :: 3.3
Classifier: Topic :: Software Development :: Testing
Classifier: Natural Language :: English
Classifier: Intended Audience :: Developers
